<?xml version="1.0"?>
<record where="h" when="1196960402" ordinal="31" title="PERSONAL EXPLANATION">
  <narrative>PERSONAL EXPLANATION -- (House of Representatives - December 06, 2007)&lt;p&gt;&lt;center&gt;&lt;pre&gt;[Page: H14445]</narrative>
  <speaking speaker="400302" topic="">
    <paragraph>Mr. Speaker, due to important business in my district, I was unable to vote during the following rollcall votes. Had I been present, I would have voted as indicated below.</paragraph>
    <paragraph>Rollcall No. 1131: "yea"; rollcall No. 1132: "yea"; rollcall No. 1133: "yea"; rollcall No. 1134: "yea"; rollcall No. 1135: "yea"; rollcall No. 1136: "nay"; rollcall No. 1137: "nay"; rollcall No. 1138: "yea"; rollcall No. 1139: "present"; rollcall No. 1140: "nay"; and rollcall No. 1141: "yea".</paragraph>
  </speaking>
</record>
