<?xml version="1.0"?>
<record where="s" when="1213804802" ordinal="55" title="PROGRAM">
  <narrative>PROGRAM -- (Senate - June 18, 2008)&lt;p&gt;&lt;center&gt;&lt;pre&gt;[Page: <bill type="s" number="5769">S5769</bill>]</narrative>
  <speaking speaker="400619" topic="">
    <paragraph>Madam President, tomorrow we expect to begin legislating on the very important housing legislation. Senators should be prepared to vote throughout the day in relation to amendments to the bill.</paragraph>
  </speaking>
</record>
