<?xml version="1.0"?>
<record where="s" when="1205337602" ordinal="41" title="ORDERS FOR THURSDAY, MARCH 13, 2008">
  <narrative>ORDERS FOR THURSDAY, MARCH 13, 2008 -- (Senate - March 12, 2008)&lt;p&gt;&lt;center&gt;&lt;pre&gt;[Page: <bill type="s" number="2029">S2029</bill>]</narrative>
  <speaking speaker="412246" topic="">
    <paragraph>Mr. President, I ask unanimous consent that when the Senate completes its business today, it stand adjourned until 10:15 a.m. tomorrow, Thursday, March 13; that following the prayer and pledge, the Journal of proceedings be approved to date, the morning hour be deemed expired, the leader time be reserved for their use later in the day, and that there be a moment of silence to honor the 5 years of service and sacrifice of our troops and their families for the war in Iraq and also to  remember those who are serving our Nation in Afghanistan and throughout the world; that following the moment of silence, the Senate resume consideration of <bill type="sc" number="70">S. Con. Res. 70</bill>, the concurrent resolution on the budget, under the previous order.</paragraph>
  </speaking>
  <chair> Without objection, it is so ordered.</chair>
</record>
