<?xml version="1.0"?>
<record where="s" when="1182268804" ordinal="6" title="MEASURE PLACED ON CALENDAR--S. 1639">
  <speaking speaker="300082" topic="">
    <paragraph>Madam President, I understand that <bill type="s" number="1639">S. 1639</bill> is at the desk and is due for a second reading.</paragraph>
  </speaking>
  <chair> The clerk will report the bill by title.</chair>
  <speaking speaker="300082" topic="">
    <paragraph>I would object to further proceedings at this time.</paragraph>
  </speaking>
  <chair> Objection is heard. Under rule XIV, the bill will be placed on the calendar.</chair>
</record>
