<?xml version="1.0"?>
<record where="s" when="1185336000" ordinal="47" title="AUTHORIZING PRINTING OF BROCHURE">
  <narrative>AUTHORIZING PRINTING OF BROCHURE -- (Senate - July 25, 2007)&lt;p&gt;&lt;center&gt;&lt;pre&gt;[Page: <bill type="s" number="10045">S10045</bill>]</narrative>
  <speaking speaker="300076" topic="">
    <paragraph>Mr. President, I ask unanimous consent that the Senate now proceed to the immediate consideration of <bill type="hc" number="190">H. Con. Res. 190</bill>, just received from the House and is at the desk.</paragraph>
  </speaking>
  <chair> The clerk will report the concurrent resolution by title.</chair>
  <narrative>The legislative clerk read as follows:</narrative>
  <narrative>A concurrent resolution (<bill type="hc" number="190">H. Con. Res. 190</bill>) authorizing printing of the brochure entitled  "How Our Laws Are Made", the document-sized, annotated version of the United States Constitution, and the pocket version of the United States Constitution.</narrative>
  <narrative>There being no objection, the Senate proceeded to consider the concurrent resolution.</narrative>
  <speaking speaker="300076" topic="">
    <paragraph>Mr. President, I ask unanimous consent that the concurrent resolution be agreed to, and the motion to reconsider be laid upon the table, without intervening action or debate.</paragraph>
  </speaking>
  <chair> Without objection, it is so ordered.</chair>
  <chair>The concurrent resolution (<bill type="hc" number="190">H. Con. Res. 190</bill>) was agreed to.</chair>
</record>
