<?xml version="1.0"?>
<record where="s" when="1222099204" ordinal="72" title="ORDERS FOR TUESDAY, SEPTEMBER 23, 2008">
  <narrative>ORDERS FOR TUESDAY, SEPTEMBER 23, 2008 -- (Senate - September 22, 2008)&lt;p&gt;&lt;center&gt;&lt;pre&gt;[Page: <bill type="s" number="9220">S9220</bill>]</narrative>
  <speaking speaker="300082" topic="">
    <paragraph>Mr. President, I ask unanimous consent that when the Senate completes its business today, it stand in recess until 10 a.m., September 23; that following the prayer and pledge, the Journal of proceedings be approved to date, the time for the two leaders be reserved for their use later in the day, and the Senate then proceed to a period for the transaction of morning business for up to 1 hour, with Senators permitted to speak for up 10 minutes each, with the time equally divided and controlled  between the two leaders or their designees, with the Republicans controlling the first half and the majority controlling the second half; that following morning business, the Senate proceed to the consideration of <bill type="h" number="6049">H.R. 6049</bill>, the tax extenders legislation, under the previous order; further, that the Senate recess from 12:30 p.m. to 2:15 p.m. to allow for the weekly caucus luncheons.</paragraph>
  </speaking>
  <chair> Without objection, it is so ordered.</chair>
</record>
