<?xml version="1.0"?>
<record where="s" when="1203958802" ordinal="7" title="UNANIMOUS-CONSENT AGREEMENT--S. 1200">
  <narrative>UNANIMOUS-CONSENT AGREEMENT--S. 1200 -- (Senate - February 25, 2008)&lt;p&gt;&lt;center&gt;&lt;pre&gt;[Page: <bill type="s" number="1098">S1098</bill>]</narrative>
  <speaking speaker="300082" topic="">
    <paragraph>Mr. President, I ask unanimous consent that the previous order with respect to <bill type="h" number="1328">H.R. 1328</bill> be vitiated and that the Senate vote on passage of <bill type="s" number="1200">S. 1200</bill>, as amended; further, that any order that would have occurred on passage of <bill type="h" number="1328">H.R. 1328</bill> now be effective on passage of <bill type="s" number="1200">S. 1200</bill>, and that all other provisions of previous orders remain in effect.</paragraph>
  </speaking>
  <chair> Is there objection?</chair>
  <chair>Without objection, it is so ordered.</chair>
</record>
