<?xml version="1.0" encoding="ISO-8859-1"?>
<speeches id='400359'>
<cr file="110/h20070516-30" where="h" when="1179331205" ordinal="30" title="Personal Explanation" topics="Personal Explanation: MILITARY OFFICERS, NOTICE TO ALTER ORDER OF CONSIDERATION OF AMENDMENTS, ANNOUNCEMENT BY THE ACTING CHAIRMAN" excerpt="Thank you very much, Mr. Hunter, for yielding. Mr. Chairman, one of the provisions that is contained in this en bloc amendment is a provision that will help provide a higher level of security for our military personnel in the continental United States. As most of you probably read in the newspaper, a terrorist cell was apprehended in Cherry ..." words="522" />
<cr file="110/h20070419-30" where="h" when="1176998405" ordinal="30" title="Appointment of Conferees on H.R. 1591, U.S. Troop Readiness, Veterans' Health and Iraq Accountability Act, 2007" topics="Appointment of Conferees on H.R. 1591, U.S. Troop Readiness, Veterans' Health and Iraq Accountability Act, 2007: MOTION TO INSTRUCT OFFERED BY MR." excerpt="I would like to thank Mr. Lewis for yielding time. Mr. Speaker, this vote to me is about Jacqueline, Kate and Allie. Most of you don't know Jacqueline, Kate and Allie. You see, they are my granddaughters, the next generation, the generation that will perhaps be most affected by this policy. To many in this Chamber, I am afraid this ..." words="549" />
<cr file="110/h20070328-32" where="h" when="1175097624" ordinal="32" title="Wounded Warrior Assistance Act of 2007" topics="Wounded Warrior Assistance Act of 2007: IN THE COMMITTEE OF THE WHOLE" excerpt="Mr. Chairman, I thank the gentleman from San Diego for yielding me this time. I rise in support of this legislation and want to highlight two key components of the Wounded Warrior Assistance Act that have significant relevance to some of my own constituents who are currently recovering at Walter Reed Mologne House. Section 101 of the..." words="549" />
<cr file="110/h20070214-29" where="h" when="1171472405" ordinal="29" title="Iraq War Resolution" topics="Iraq War Resolution: IN CLOSING" excerpt="Mr. Speaker, I thank the gentleman for yielding me time. First, let me begin by saying that I have observed several speakers here during this debate who I am sure in good faith made the representations that they did, that the short-term redeployment or surge was not a recommendation of the Iraq Study Group. This is a copy of the report..." words="2374" />
<cr file="110/h20070712-29" where="h" when="1184212800" ordinal="29" title="Responsible Redeployment from Iraq Act" topics="" excerpt="Mr. Speaker, I thank the gentleman for yielding. Mr. Speaker, I rise with great respect for the chairman of the Armed Services Committee and the author of this bill, but with strong opposition to H.R. 2956. Mr. Speaker, the short title of this bill is the &quot;Responsible Redeployment from Iraq Act.&quot; But, Mr. Speaker, this bill is not..." words="991" />
<cr file="110/h20070215-26" where="h" when="1171515600" ordinal="26" title="Iraq War Resolution" topics="Iraq War Resolution: LEGISLATIVE PROGRAM" excerpt="Madam Speaker, I yield 3 minutes to the gentleman from Texas (Mr. Smith)." words="365" />
<cr file="110/h20070516-35" where="h" when="1179331205" ordinal="35" title="National Defense Authorization Act For Fiscal Year 2008" topics="" excerpt="Madam Chairman, I rise in support of this amendment for two very important reasons. First, there is a growing threat. Today's Herald Tribune, a newspaper owned by The New York Times, says that North Korea is developing new, long-range missiles capable of hitting Guam, an article from the Herald Tribune. The second set of reasons that I..." words="438" />
<cr file="110/h20070905-30" where="h" when="1189008002" ordinal="30" title="Recognizing the Strong Security Alliance Between Japan and The United States" topics="" excerpt="Let me thank the gentlelady for yielding. And let me begin by thanking my good friend and colleague, Chairman TOM LANTOS, for the great high level of cooperation that was exhibited on this resolution on a bipartisan basis with Ms. Ros-Lehtinen and others. And also, let me acknowledge the great support of my friend, Mr. Faleomavaega, on the..." words="412" />
<cr file="110/h20070516-29" where="h" when="1179331205" ordinal="29" title="National Defense Authorization Act For Fiscal Year 2008" topics="National Defense Authorization Act For Fiscal Year 2008: ANNOUNCEMENT BY THE CHAIRMAN" excerpt="Mr. Chairman, I yield myself 4 minutes. Mr. Chairman, the process that we've gone through to bring this bill to the floor has been an extensive one. We started under the leadership of Chairman Skelton in January, and as we moved through the days and the weeks, there were numerous, both full committee and subcommittee hearings. There..." words="575" />
<cr file="110/h20070213-39" where="h" when="1171386003" ordinal="39" title="Iraq War Resolution" topics="Iraq War Resolution: PRESIDENTIAL DETERMINATION.--" excerpt="I yield to the gentleman" words="2904" />
<cr file="110/h20070418-36" where="h" when="1176912003" ordinal="36" title="Honoring the 53,000 Soldiers, Sailors, Airmen, Marines, and Civilians That Comprise the Nation's Special Operations Forces Community" topics="" excerpt="Mr. Speaker, I have the highest regard for every man and woman who serves in the United States military. Whether they be a member of the Air Force or the Army or the Marine Corps or the Navy or the Coast Guard, everyone who volunteers to serve our country deserves the gratitude of every American citizen. And to the extent that they have..." words="531" />
<cr file="110/h20080116-28" where="h" when="1200502802" ordinal="28" title="National Defense Authorization Act For Fiscal Year 2008" topics="" excerpt="Madam Speaker, we have no further speakers on our side, and I yield back the balance of my time." words="771" />
<cr file="110/h20080922-30" where="h" when="1222099204" ordinal="30" title="Coastal and Estuarine Land Conservation Program Act" topics="" excerpt="Mr. Speaker, I rise today to urge my colleagues to join me in supporting authorization of the Coastal and Estuarine Land Conservation Program. H.R. 1907--the Coastal and Estuarine Land Conservation Program Act authorizes a voluntary partnership program to provide badly needed Federal funds for the purchase and protection of sensitive coastal..." words="486" />
</speeches>
