<?xml version="1.0" encoding="ISO-8859-1"?>
<speeches id='412215'>
<cr file="110/h20071024-50" where="h" when="1193241604" ordinal="50" title="Constitutional Checks and Balances" topics="" excerpt="Mr. Speaker, when I think about article I, I think this passage in the Federalist Papers where it says that we are to be in intimate sympathy with the people, I got to tell you, that when I sat down along with my colleague Congressman Hodes and Congressman Klein with the Financial Services Committee to listen to people who had faced foreclosure ..." words="961" />
<cr file="110/h20070419-47" where="h" when="1176998405" ordinal="47" title="The Accountability Congress: The 110th Congress" topics="" excerpt="Mr. Speaker, we are going to wrap it up right now. I want you to know that this class of 2006, this 110th Congress, is pointing the way forward for a better America today, tomorrow and in the future. Thank you all very much." words="1752" />
<cr file="110/h20070326-49" where="h" when="1174924955" ordinal="49" title="Failed Trade Policy" topics="" excerpt="Thank you. I thank you for your leadership on this issue of fair trade. I think that the time is right, the time is now to begin talking about fair trade. I want to commend all of the Members here tonight talking about this critical issue. This election sent a strong message: no staying the course on Bush's failed trade policy. So now what..." words="764" />
<cr file="110/h20080513-56" where="h" when="1210694402" ordinal="56" title="Requiring a Voter's Photo Id Will Deny Many American Citizens from Their Right to Vote" topics="" excerpt="Madam Speaker, it was on May 7, the day of the Indiana primary election just last Tuesday, I believe that was May 5, excuse me, May 5, that 12 nuns came to the voting booth to cast a ballot in the election. These nuns, women of the cloth, women who have dedicated their lives to prayer and service, only wanted to vote but were barred from doing..." words="902" />
<cr file="110/h20080507-59" where="h" when="1210176002" ordinal="59" title="Neighborhood Stabilization Act of 2008" topics="Neighborhood Stabilization Act of 2008: IN THE COMMITTEE OF THE WHOLE" excerpt="Madam Chairman, let me start by thanking Chairman Frank and Chairwoman Waters for bringing this critical and much-needed legislation to the floor. I'm proud to have worked with both of them on this important legislation which represents the most comprehensive response yet in the American mortgage crisis. The package of housing measures that ..." words="370" />
<cr file="110/h20070919-49" where="h" when="1190217601" ordinal="49" title="Majority Makers" topics="" excerpt="Mr. Speaker, I am really honored to join my members of this freshman class. I am so proud to be a Member of the 110th Congress. I just wanted to point out that this week as we contemplate and as we've seen the three reports, the GAO report, the report from General Petraeus, the report from General Jones, we are at a point where we have to..." words="927" />
<cr file="110/h20071003-61" where="h" when="1191427202" ordinal="61" title="Schip" topics="" excerpt="That's right." words="2538" />
<cr file="110/h20071002-36" where="h" when="1191340802" ordinal="36" title="Recognizing Commencement of Ramadan and Commending Muslims For Their Faith" topics="" excerpt="Mr. Speaker, let me thank the gentleman for yielding time and for this excellent resolution. I'd like to thank all of the authors, including Congresswoman Eddie Bernice Johnson and everyone who signed on to the resolution commemorating the month of Ramadan. I am celebrating Ramadan myself personally, and I have been doing so ever since my..." words="534" />
<cr file="110/h20071024-45" where="h" when="1193241604" ordinal="45" title="Honoring the Life of Senator Paul Wellstone" topics="" excerpt="Mr. Speaker, I would like to call to the House's attention that it was on October 25 a few years ago, not long it seems, only days ago, in 2002 that our State of Minnesota lost Senator Paul Wellstone. Paul Wellstone, Mr. Speaker, was a United States Senator, was a professor of politics, political science, at Carleton College. Paul Wellstone ..." words="716" />
<cr file="110/h20070905-39" where="h" when="1189008002" ordinal="39" title="Honoring the City of Minneapolis, First Responders, and The Citizens of Minnesota For Their Valiant Efforts In Responding to The Collapse of The Interstate Route 35w Mississippi River Bridge" topics="" excerpt="Madam Speaker, I am proud to rise on the floor today to speak on behalf of H. Res. 606, a resolution that honors the city of Minneapolis and the first responders and citizens of Minnesota for their valiant efforts in responding to the horrific collapse of Interstate 35W Mississippi River bridge. Madam Speaker, while we honor the city of..." words="470" />
<cr file="110/h20071031-49" where="h" when="1193846401" ordinal="49" title="Accomplishments of The 110th Congress" topics="" excerpt="Thank you, Congressman Klein. Whether it be from Colorado to Vermont, from Kentucky to Tennessee, to Minnesota, to Florida, no matter where we come from, this freshman class that we belong to is here to stay and here to say, very clearly, that we are reclaiming the coequal branch of this legislative body in our constitutional framework. We don't..." words="560" />
<cr file="110/h20070111-71" where="h" when="1168534804" ordinal="71" title="The War In Iraq" topics="" excerpt="I thank the gentlewoman from California for allowing me to participate in the Out of Iraq Caucus. I do formally request membership in such caucus at this moment and anxiously await being a full-fledged member of the Out of Iraq Caucus. Mr. Speaker and Members, I rise today really in the mindset of this coming weekend, which is Martin Luther ..." words="527" />
<cr file="110/h20070314-62" where="h" when="1173888004" ordinal="62" title="Oversight and Accountability In Government" topics="" excerpt="Congresswoman Sutton, it is a great honor to be here with you tonight together with our other colleagues in the freshman class who will be speaking in just a moment because I think it is important that the American people know that the freshman members of the Democratic Caucus came to this Congress, not to occupy space, not to warm a seat, but..." words="1450" />
<cr file="110/h20070521-50" where="h" when="1179763212" ordinal="50" title="Trade and Labor" topics="" excerpt="Mr. Hare, thank you for leading us in this very important Special Order tonight. Trade is one of the critical issues facing our Nation. Let me say that on the campaign trail, Mr. Speaker, I found myself talking about jobs, employment, and opportunity to people on a daily basis. Whether I went to the suburban areas or the heart of..." words="1301" />
<cr file="110/h20070208-44" where="h" when="1170910800" ordinal="44" title="The Painful Cost of The President's Budget" topics="" excerpt="Madam Speaker, on Monday, the President submitted his budget for our Nation. In that budget, it would be easy to look at it and say, this is all about numbers, it is just a rational approach, it is just a plan, it is an impersonal thing. But, in fact, Madam Speaker, what a budget is is a moral statement about who matters in our society...." words="787" />
<cr file="110/h20070119-48" where="h" when="1169226004" ordinal="48" title="The American People Took Back Their Government" topics="" excerpt="Mr. Speaker, today I rise to lend my voice with all of the people who voted for a change for America, but especially to lend my voice with my fellow new Congressmen, the freshmen. I rise because I believe that we were sent here to pursue an agenda for America, to set our country on a new course, a new course which put the public good at the..." words="411" />
<cr file="110/h20070215-26" where="h" when="1171515600" ordinal="26" title="Iraq War Resolution" topics="Iraq War Resolution: LEGISLATIVE PROGRAM" excerpt="Madam Speaker, make no mistake about it, the change that took place in this body over the course of November 7 is directly related to this war in Iraq. And the presence of a number of people who are here now is directly related to the will of the American people to end this war, which never should have been started. The fact is, the..." words="936" />
<cr file="110/h20080402-61" where="h" when="1207152003" ordinal="61" title="The Economy" topics="" excerpt="The Great Depression. I am telling you, the signs are not good. We need bold, decisive action which puts the public sector and the private sector in a partnership to look out for the American consumer. This is what we have to do. You know, Mr. Yarmuth, let me talk to you a little bit about some things you inspired me to think about...." words="694" />
<cr file="110/h20070712-62" where="h" when="1184212800" ordinal="62" title="Discussing the War In Iraq" topics="" excerpt="No doubt, Mr. Speaker. That's an excellent point. What does it mean to care for a 20-year-old quadriplegic for the course of his or her life? This chart speaks for itself, but I just want to go to the bottom line if I may, Mr. Speaker. We're looking at $3,816 per second." words="705" />
<cr file="110/h20071016-64" where="h" when="1192550402" ordinal="64" title="Tribute to Vernon Bellecourt" topics="" excerpt="Mr. Speaker, today I rise to pay tribute to the life of Vernon Bellecourt of Minnesota, a selfless servant who committed his life not just to fight for American Indians but for the rights of all people. Last night I was at a funeral service for Mr. Bellecourt, and while I regret to report the recent passing of Mr. Bellecourt at age 75, I am ..." words="647" />
<cr file="110/h20070726-58" where="h" when="1185422400" ordinal="58" title="Majority Maker Freshmen" topics="" excerpt="Madam Speaker, this is going to conclude our Special Order hour. The difference-makers are going to be on the job for the American people. We can be counted on to make that difference that we were brought here to make. And, Madam Speaker, I just think it's important for the American people to know that this Democratic caucus will be standing up ..." words="1370" />
<cr file="110/h20080116-50" where="h" when="1200502802" ordinal="50" title="The State of The Economy" topics="" excerpt="How about little Gus, your son?" words="1249" />
<cr file="110/h20070118-63" where="h" when="1169139604" ordinal="63" title="Recounting Reasons For Voting In Favor of 2002 Resolution Authorizing Use of Military Force In Iraq" topics="" excerpt="I thank the gentlewoman from California. And I was told early on, Madam Speaker, that the gentlewoman from California wanted to feature Congress people who had voted for the war in Iraq and then had subsequently changed their minds. I was persistent in trying to be a part of tonight's special order, and I thank the gentlewoman from California..." words="837" />
<cr file="110/h20070507-56" where="h" when="1178553612" ordinal="56" title="Asian Pacific American Heritage Month" topics="" excerpt="Mr. Speaker, this month marks a special opportunity to pay tribute to the contributions of Asian Americans and Pacific Islander Americans. In our community, we have a great opportunity to recognize this dynamic force of creativity in our Nation, and I welcome the opportunity to do so and I thank my colleague Mike Honda for hosting this special..." words="563" />
<cr file="110/h20070618-58" where="h" when="1182182403" ordinal="58" title="Fast Track Trade" topics="" excerpt="Will the gentlelady yield? I agree. American workers are some of the best in the world, innovative, hard-working, no doubt about it, and given a fair chance, can compete with any workers or anyone around the world, but we just need a fair opportunity. So I think we need a new model, a new way of doing business that will protect American workers ..." words="1367" />
<cr file="110/h20070305-47" where="h" when="1173114004" ordinal="47" title="The Economy" topics="" excerpt="Fair trade." words="826" />
<cr file="110/h20071107-41" where="h" when="1194454802" ordinal="41" title="Providing For Consideration of H.R. 3688, United States-Peru Trade Promotion Agreement Implementation Act" topics="" excerpt="Mr. Speaker, like many of my colleagues, I am for fair trade, not simply free trade. And I would associate myself with comments already made today, &quot;free trade for free people.&quot; Yet already reported recently, miners in Peru are facing having their strike declared illegal and shut down. That doesn't sound very free to me. This Peru FTA, I..." words="423" />
</speeches>
